{"23559":{"taxa_exame":1.1,"taxa_20min":35.2,"total":88,"exames":1,"menos20":31},"38162":{"taxa_exame":7.7,"taxa_20min":30.8,"total":13,"exames":1,"menos20":4},"46118":{"taxa_exame":5.6,"taxa_20min":22.2,"total":18,"exames":1,"menos20":4},"65995":{"taxa_exame":8.3,"taxa_20min":54.2,"total":24,"exames":2,"menos20":13},"66057":{"taxa_exame":25,"taxa_20min":40.4,"total":52,"exames":13,"menos20":21},"69038":{"taxa_exame":35.3,"taxa_20min":35.3,"total":17,"exames":6,"menos20":6},"73843":{"taxa_exame":25,"taxa_20min":43.8,"total":16,"exames":4,"menos20":7},"75535":{"taxa_exame":14.3,"taxa_20min":42.9,"total":7,"exames":1,"menos20":3},"76443":{"taxa_exame":40,"taxa_20min":70,"total":10,"exames":4,"menos20":7},"81655":{"taxa_exame":24.1,"taxa_20min":44.8,"total":29,"exames":7,"menos20":13},"85248":{"taxa_exame":20,"taxa_20min":40,"total":30,"exames":6,"menos20":12},"94563":{"taxa_exame":13.3,"taxa_20min":43.3,"total":30,"exames":4,"menos20":13},"96791":{"taxa_exame":36.4,"taxa_20min":18.2,"total":11,"exames":4,"menos20":2},"97894":{"taxa_exame":0,"taxa_20min":0,"total":2,"exames":0,"menos20":0},"104454":{"taxa_exame":7.7,"taxa_20min":38.5,"total":13,"exames":1,"menos20":5},"122157":{"taxa_exame":25,"taxa_20min":62.5,"total":8,"exames":2,"menos20":5},"123813":{"taxa_exame":0,"taxa_20min":16.7,"total":6,"exames":0,"menos20":1},"124350":{"taxa_exame":20,"taxa_20min":10,"total":10,"exames":2,"menos20":1},"140430":{"taxa_exame":0,"taxa_20min":100,"total":1,"exames":0,"menos20":1},"146653":{"taxa_exame":0,"taxa_20min":0,"total":1,"exames":0,"menos20":0},"148748":{"taxa_exame":33.3,"taxa_20min":30.8,"total":39,"exames":13,"menos20":12},"149400":{"taxa_exame":38.5,"taxa_20min":61.5,"total":13,"exames":5,"menos20":8},"157370":{"taxa_exame":14.3,"taxa_20min":42.9,"total":14,"exames":2,"menos20":6},"160299":{"taxa_exame":25,"taxa_20min":38.6,"total":44,"exames":11,"menos20":17},"170189":{"taxa_exame":9.7,"taxa_20min":61.3,"total":31,"exames":3,"menos20":19},"179374":{"taxa_exame":33.3,"taxa_20min":44.4,"total":9,"exames":3,"menos20":4},"189313":{"taxa_exame":28.6,"taxa_20min":28.6,"total":21,"exames":6,"menos20":6},"191475":{"taxa_exame":5.6,"taxa_20min":77.8,"total":18,"exames":1,"menos20":14},"192500":{"taxa_exame":25,"taxa_20min":37.5,"total":8,"exames":2,"menos20":3},"193059":{"taxa_exame":25,"taxa_20min":68.8,"total":16,"exames":4,"menos20":11},"193490":{"taxa_exame":0,"taxa_20min":0,"total":2,"exames":0,"menos20":0},"200421":{"taxa_exame":0,"taxa_20min":12.5,"total":8,"exames":0,"menos20":1},"203231":{"taxa_exame":0,"taxa_20min":100,"total":1,"exames":0,"menos20":1},"207165":{"taxa_exame":0,"taxa_20min":100,"total":3,"exames":0,"menos20":3},"207264":{"taxa_exame":33.3,"taxa_20min":16.7,"total":6,"exames":2,"menos20":1},"207389":{"taxa_exame":0,"taxa_20min":20,"total":5,"exames":0,"menos20":1},"209169":{"taxa_exame":5.9,"taxa_20min":61.8,"total":34,"exames":2,"menos20":21},"210085":{"taxa_exame":26.9,"taxa_20min":65.4,"total":26,"exames":7,"menos20":17},"211672":{"taxa_exame":7.1,"taxa_20min":50,"total":28,"exames":2,"menos20":14},"212621":{"taxa_exame":9.1,"taxa_20min":45.5,"total":11,"exames":1,"menos20":5},"212833":{"taxa_exame":14.3,"taxa_20min":14.3,"total":7,"exames":1,"menos20":1},"213110":{"taxa_exame":18.4,"taxa_20min":53.1,"total":49,"exames":9,"menos20":26},"214239":{"taxa_exame":34.5,"taxa_20min":55.2,"total":29,"exames":10,"menos20":16},"214600":{"taxa_exame":21.4,"taxa_20min":85.7,"total":14,"exames":3,"menos20":12},"214747":{"taxa_exame":0,"taxa_20min":50,"total":4,"exames":0,"menos20":2},"218638":{"taxa_exame":14.3,"taxa_20min":51.4,"total":35,"exames":5,"menos20":18},"220802":{"taxa_exame":0,"taxa_20min":50,"total":6,"exames":0,"menos20":3},"222076":{"taxa_exame":0,"taxa_20min":50,"total":2,"exames":0,"menos20":1},"226882":{"taxa_exame":26.1,"taxa_20min":52.2,"total":23,"exames":6,"menos20":12},"229560":{"taxa_exame":0,"taxa_20min":25,"total":8,"exames":0,"menos20":2},"234277":{"taxa_exame":30.8,"taxa_20min":64.1,"total":39,"exames":12,"menos20":25},"237083":{"taxa_exame":14.3,"taxa_20min":42.9,"total":14,"exames":2,"menos20":6},"237126":{"taxa_exame":0,"taxa_20min":0,"total":1,"exames":0,"menos20":0}}